{
    "ELEC5618-S1C-ND-CC|Lecture|01": {
        "displaySubjectCode": "ELEC5618-S1C-ND-CC",
        "subject_code": "ELEC5618-S1C-ND-CC",
        "activity_group_code": "Lecture",
        "activity_code": "01",
        "campus": "CC",
        "campus_description": "Camperdown\/Darlington, Sydney",
        "day_of_week": "Thu",
        "start_time": "17:00",
        "location": "H04.01.131.Merewether Building.Merewether Lecture Theatre (1) 131",
        "duration": "120",
        "adjusted_size": 330,
        "student_count": 289,
        "availability": 41,
        "week_pattern": "0000000011111111011111000000000000000000000000000000",
        "description": "Lecture (on-campus)",
        "zone": "CC - Camperdown\/Darlington",
        "department": "Electrical and Computer Engineering",
        "semester": "S1C",
        "semester_description": "Semester 1",
        "activityType": "Lecture",
        "rp_constrained": false,
        "selectable": "available",
        "seats_for_student": 41,
        "start_date": "30\/12\/2024",
        "color": "#e5e5e5",
        "activitiesDays": [
            "27\/2\/2025",
            "6\/3\/2025",
            "13\/3\/2025",
            "20\/3\/2025",
            "27\/3\/2025",
            "3\/4\/2025",
            "10\/4\/2025",
            "17\/4\/2025",
            "1\/5\/2025",
            "8\/5\/2025",
            "15\/5\/2025",
            "22\/5\/2025",
            "29\/5\/2025"
        ],
        "lat": "-33.88880123",
        "lng": "151.1922161",
        "locations": [
            {
                "id": "H04.01.131",
                "description": "H04.131.Merewether Building.Merewether Lecture Theatre (1) 131",
                "lat": "-33.88880123",
                "lng": "151.1922161",
                "activityDays": [
                    "27\/2\/2025",
                    "6\/3\/2025",
                    "13\/3\/2025",
                    "20\/3\/2025",
                    "27\/3\/2025",
                    "3\/4\/2025",
                    "10\/4\/2025",
                    "17\/4\/2025",
                    "1\/5\/2025",
                    "8\/5\/2025",
                    "15\/5\/2025",
                    "22\/5\/2025",
                    "29\/5\/2025"
                ]
            }
        ],
        "timezone": "Australia\/Sydney",
        "isOnlineAct": false,
        "record_attendance": false,
        "attendanceStudent": "540273917",
        "attendanceStatus": "",
        "attendanceUpdatedBy": "",
        "qualify": "",
        "clash-ignore": []
    },
    "ELEC5618-S1C-ND-CC|Lecture|02": {
        "displaySubjectCode": "ELEC5618-S1C-ND-CC",
        "subject_code": "ELEC5618-S1C-ND-CC",
        "activity_group_code": "Lecture",
        "activity_code": "02",
        "campus": "CC",
        "campus_description": "Camperdown\/Darlington, Sydney",
        "day_of_week": "Thu",
        "start_time": "17:00",
        "location": "-",
        "duration": "120",
        "adjusted_size": 270,
        "student_count": 270,
        "availability": 0,
        "week_pattern": "0000000011111111011111000000000000000000000000000000",
        "description": "Lecture (online)",
        "zone": "-",
        "department": "Electrical and Computer Engineering",
        "semester": "S1C",
        "semester_description": "Semester 1",
        "activityType": "Online Lecture*",
        "rp_constrained": false,
        "selectable": "full",
        "seats_for_student": 0,
        "start_date": "30\/12\/2024",
        "color": "#",
        "activitiesDays": [
            "27\/2\/2025",
            "6\/3\/2025",
            "13\/3\/2025",
            "20\/3\/2025",
            "27\/3\/2025",
            "3\/4\/2025",
            "10\/4\/2025",
            "17\/4\/2025",
            "1\/5\/2025",
            "8\/5\/2025",
            "15\/5\/2025",
            "22\/5\/2025",
            "29\/5\/2025"
        ],
        "lat": "",
        "lng": "",
        "locations": [],
        "timezone": "Australia\/Sydney",
        "isOnlineAct": false,
        "record_attendance": false,
        "attendanceStudent": "540273917",
        "attendanceStatus": "",
        "attendanceUpdatedBy": "",
        "qualify": "Allocation disqualified[540273917]: already allocated activity - 540273917\/ELEC5618-S1C-ND-CC\/Lecture\/02",
        "clash-ignore": []
    }
}